edgarito/cli/__main__.py
edgarito/cli/logger.py
edgarito/cli/settings.py
edgarito/enums/edgar/filing_type.py
edgarito/schemas/edgar_responses/company_facts.py
edgarito/schemas/edgar_responses/company_ticker.py
edgarito/schemas/edgar_responses/submission.py
edgarito/schemas/edgar_responses/submission_custom.py
edgarito/services/analysis/red_flags_service.py
edgarito/services/cache/filesystem_cache.py
edgarito/services/downloader/download_service.py
edgarito/services/edgar_rest_client/low_level_client.py
edgarito/services/edgar_rest_client/submissions_client.py
edgarito/services/parser/submission_txt_extractor.py
edgarito/services/taxonomy_client/xbrl_taxonomy_client.py
edgarito-0.1.1.dist-info/LICENSE
edgarito-0.1.1.dist-info/METADATA
edgarito-0.1.1.dist-info/WHEEL
edgarito-0.1.1.dist-info/top_level.txt
edgarito-0.1.1.dist-info/RECORD
