Metadata-Version: 2.2
Name: edgarito
Version: 0.1.1
Summary: Async client for the REST API of EDGAR which returns data structured into pydantic schemas and SEC filings
Author-email: Jean-François Kener <betterask.jf@gmail.com>
Classifier: Programming Language :: Python :: 3
Classifier: License :: OSI Approved :: MIT License
Classifier: Operating System :: OS Independent
License-File: LICENSE
